prometheus_toggl_track_exporter/__init__.py
prometheus_toggl_track_exporter/__main__.py
prometheus_toggl_track_exporter/exporter.py
prometheus_toggl_track_exporter-1.2.0.dist-info/LICENSE
prometheus_toggl_track_exporter-1.2.0.dist-info/METADATA
prometheus_toggl_track_exporter-1.2.0.dist-info/WHEEL
prometheus_toggl_track_exporter-1.2.0.dist-info/entry_points.txt
prometheus_toggl_track_exporter-1.2.0.dist-info/RECORD
