Metadata-Version: 2.3
Name: prometheus-toggl-track-exporter
Version: 1.2.0
Summary: A Prometheus exporter for Toggl Track
License: MIT
Keywords: prometheus,toggl,toggl track,exporter,metrics
Author: echohello-dev
Author-email: devs@echohello.dev
Requires-Python: >=3.13,<4.0
Classifier: License :: OSI Approved :: MIT License
Classifier: Operating System :: OS Independent
Classifier: Programming Language :: Python :: 3
Classifier: Programming Language :: Python :: 3.13
Requires-Dist: prometheus-client (>=0.21.1,<0.22.0)
Requires-Dist: requests (>=2.31.0,<3.0.0)
Project-URL: Repository, https://github.com/echohello-dev/prometheus-toggl-track-exporter
